notmuch/__init__.py
notmuch/compat.py
notmuch/database.py
notmuch/directory.py
notmuch/errors.py
notmuch/filenames.py
notmuch/globals.py
notmuch/message.py
notmuch/messages.py
notmuch/query.py
notmuch/tag.py
notmuch/thread.py
notmuch/threads.py
notmuch/version.py
notmuch-0.29.2.dist-info/LICENSE
notmuch-0.29.2.dist-info/WHEEL
notmuch-0.29.2.dist-info/METADATA
notmuch-0.29.2.dist-info/RECORD
